cpu/modules.v
module ram #(parameter N=8,M=32) (input [N-1:0]addr,input [M-1:0]data,input clk,input we,output [M-1:0]dout);

    reg [M-1:0] mem [2**N-1];

always @ (posedge clk) begin
    if (we) mem[addr] <= data;
end

assign dout = mem[addr];

endmodule

cpu/main.v
`timescale 1ns / 1ns
`include "modules.v"


module main;

reg [2**8:0]addr;
reg [31:0]data;
reg clk;
reg we;
wire [31:0]dout;

ram uuf(addr,data,clk,we,dout);

always #10 clk = ~clk;

initial begin
    $dumpfile("main.vcd");
    $dumpvars(0, main);

    clk = 1;
    
    we = 1;

    for (integer i = 0;i < 2**8;i = i + 1) begin
        repeat (1) @ (posedge clk) begin
            addr <= i;
            we <= 1;
            data <= $random;
        end
    end

    we = 0;

    for (integer i = 0;i < 2**8;i = i + 1) begin
        repeat (1) @ (posedge clk) begin
            addr <= i;
            $display("%H | %h\n",addr,dout);
        end
    end
    #20;
    $finish;
end
endmodule

cpu/main.vcd
$date
	Thu Dec  1 13:04:33 2022
$end
$version
	Icarus Verilog
$end
$timescale
	1ns
$end
$scope module main $end
$var wire 32 ! dout [31:0] $end
$var reg 257 " addr [256:0] $end
$var reg 1 # clk $end
$var reg 32 $ data [31:0] $end
$var reg 1 % we $end
$scope module uuf $end
$var wire 8 & addr [7:0] $end
$var wire 1 # clk $end
$var wire 32 ' data [31:0] $end
$var wire 32 ( dout [31:0] $end
$var wire 1 % we $end
$var parameter 32 ) M $end
$var parameter 32 * N $end
$upscope $end
$scope begin $ivl_for_loop0 $end
$var integer 32 + i [31:0] $end
$upscope $end
$scope begin $ivl_for_loop1 $end
$var integer 32 , i [31:0] $end
$upscope $end
$upscope $end
$enddefinitions $end
$comment Show the parameter values. $end
$dumpall
b1000 *
b100000 )
$end
#0
$dumpvars
bx ,
b0 +
bx (
bx '
bx &
1%
bx $
1#
bx "
bx !
$end
#10
0#
#20
b0 &
b10010000101010011010100100100 $
b10010000101010011010100100100 '
b0 "
b1 +
1#
#30
0#
#40
b1 &
bx !
bx (
b11000000100010010101111010000001 $
b11000000100010010101111010000001 '
b1 "
b10 +
1#
#50
0#
#60
b10 &
b10000100100001001101011000001001 $
b10000100100001001101011000001001 '
b10 "
bx !
bx (
b11 +
1#
#70
0#
#80
b11 &
bx !
bx (
b10110001111100000101011001100011 $
b10110001111100000101011001100011 '
b11 "
b100 +
1#
#90
0#
#100
b100 &
b110101110010111101100001101 $
b110101110010111101100001101 '
b100 "
bx !
bx (
b101 +
1#
#110
0#
#120
b101 &
bx !
bx (
b1000110110111111001100110001101 $
b1000110110111111001100110001101 '
b101 "
b110 +
1#
#130
0#
#140
b110 &
b10110010110000101000010001100101 $
b10110010110000101000010001100101 '
b110 "
bx !
bx (
b111 +
1#
#150
0#
#160
b111 &
bx !
bx (
b10001001001101110101001000010010 $
b10001001001101110101001000010010 '
b111 "
b1000 +
1#
#170
0#
#180
b1000 &
b111100111110001100000001 $
b111100111110001100000001 '
b1000 "
bx !
bx (
b1001 +
1#
#190
0#
#200
b1001 &
bx !
bx (
b110110101111100110100001101 $
b110110101111100110100001101 '
b1001 "
b1010 +
1#
#210
0#
#220
b1010 &
b111011001000111111000101110110 $
b111011001000111111000101110110 '
b1010 "
bx !
bx (
b1011 +
1#
#230
0#
#240
b1011 &
bx !
bx (
b11110100011011100110100111101 $
b11110100011011100110100111101 '
b1011 "
b1100 +
1#
#250
0#
#260
b1100 &
b1110110110101000101011111101101 $
b1110110110101000101011111101101 '
b1100 "
bx !
bx (
b1101 +
1#
#270
0#
#280
b1101 &
bx !
bx (
b1000110001011011111011110001100 $
b1000110001011011111011110001100 '
b1101 "
b1110 +
1#
#290
0#
#300
b1110 &
b1111100111111011110100111111001 $
b1111100111111011110100111111001 '
b1110 "
bx !
bx (
b1111 +
1#
#310
0#
#320
b1111 &
bx !
bx (
b11100011001101110010010011000110 $
b11100011001101110010010011000110 '
b1111 "
b10000 +
1#
#330
0#
#340
b10000 &
b11100010111101111000010011000101 $
b11100010111101111000010011000101 '
b10000 "
bx !
bx (
b10001 +
1#
#350
0#
#360
b10001 &
bx !
bx (
b11010101000100111101001010101010 $
b11010101000100111101001010101010 '
b10001 "
b10010 +
1#
#370
0#
#380
b10010 &
b1110010101011111111011111100101 $
b1110010101011111111011111100101 '
b10010 "
bx !
bx (
b10011 +
1#
#390
0#
#400
b10011 &
bx !
bx (
b10111011110100100111001001110111 $
b10111011110100100111001001110111 '
b10011 "
b10100 +
1#
#410
0#
#420
b10100 &
b10001001001100101101011000010010 $
b10001001001100101101011000010010 '
b10100 "
bx !
bx (
b10101 +
1#
#430
0#
#440
b10101 &
bx !
bx (
b1000111111011001101101110001111 $
b1000111111011001101101110001111 '
b10101 "
b10110 +
1#
#450
0#
#460
b10110 &
b1111001001100000110100111110010 $
b1111001001100000110100111110010 '
b10110 "
bx !
bx (
b10111 +
1#
#470
0#
#480
b10111 &
bx !
bx (
b11100111011101101001011011001110 $
b11100111011101101001011011001110 '
b10111 "
b11000 +
1#
#490
0#
#500
b11000 &
b11110100000000000111101011101000 $
b11110100000000000111101011101000 '
b11000 "
bx !
bx (
b11001 +
1#
#510
0#
#520
b11001 &
bx !
bx (
b11100010110010100100111011000101 $
b11100010110010100100111011000101 '
b11001 "
b11010 +
1#
#530
0#
#540
b11010 &
b101110010110000100100101011100 $
b101110010110000100100101011100 '
b11010 "
bx !
bx (
b11011 +
1#
#550
0#
#560
b11011 &
bx !
bx (
b11011110100011100010100010111101 $
b11011110100011100010100010111101 '
b11011 "
b11100 +
1#
#570
0#
#580
b11100 &
b10010110101010110101100000101101 $
b10010110101010110101100000101101 '
b11100 "
bx !
bx (
b11101 +
1#
#590
0#
#600
b11101 &
bx !
bx (
b10110010101001110010011001100101 $
b10110010101001110010011001100101 '
b11101 "
b11110 +
1#
#610
0#
#620
b11110 &
b10110001111011110110001001100011 $
b10110001111011110110001001100011 '
b11110 "
bx !
bx (
b11111 +
1#
#630
0#
#640
b11111 &
bx !
bx (
b101011100111000011100001010 $
b101011100111000011100001010 '
b11111 "
b100000 +
1#
#650
0#
#660
b100000 &
b11000000001110110010001010000000 $
b11000000001110110010001010000000 '
b100000 "
bx !
bx (
b100001 +
1#
#670
0#
#680
b100001 &
bx !
bx (
b10000011001000010000100100000 $
b10000011001000010000100100000 '
b100001 "
b100010 +
1#
#690
0#
#700
b100010 &
b1010101011110000100010110101010 $
b1010101011110000100010110101010 '
b100010 "
bx !
bx (
b100011 +
1#
#710
0#
#720
b100011 &
bx !
bx (
b11001110110011001100110010011101 $
b11001110110011001100110010011101 '
b100011 "
b100100 +
1#
#730
0#
#740
b100100 &
b11001011001000000011111010010110 $
b11001011001000000011111010010110 '
b100100 "
bx !
bx (
b100101 +
1#
#750
0#
#760
b100101 &
bx !
bx (
b10001001100000111011100000010011 $
b10001001100000111011100000010011 '
b100101 "
b100110 +
1#
#770
0#
#780
b100110 &
b10000110101111000011100000001101 $
b10000110101111000011100000001101 '
b100110 "
bx !
bx (
b100111 +
1#
#790
0#
#800
b100111 &
bx !
bx (
b10101001101001111101011001010011 $
b10101001101001111101011001010011 '
b100111 "
b101000 +
1#
#810
0#
#820
b101000 &
b110101100111111101110101101011 $
b110101100111111101110101101011 '
b101000 "
bx !
bx (
b101001 +
1#
#830
0#
#840
b101001 &
bx !
bx (
b11101010101001100010101011010101 $
b11101010101001100010101011010101 '
b101001 "
b101010 +
1#
#850
0#
#860
b101010 &
b10000001000101110100101000000010 $
b10000001000101110100101000000010 '
b101010 "
bx !
bx (
b101011 +
1#
#870
0#
#880
b101011 &
bx !
bx (
b11010111010101100011111010101110 $
b11010111010101100011111010101110 '
b101011 "
b101100 +
1#
#890
0#
#900
b101100 &
b1110111111111110100100011101 $
b1110111111111110100100011101 '
b101100 "
bx !
bx (
b101101 +
1#
#910
0#
#920
b101101 &
bx !
bx (
b11100111110001010111001011001111 $
b11100111110001010111001011001111 '
b101101 "
b101110 +
1#
#930
0#
#940
b101110 &
b10001100001000100100100100011 $
b10001100001000100100100100011 '
b101110 "
bx !
bx (
b101111 +
1#
#950
0#
#960
b101111 &
bx !
bx (
b101000010010110010100001010 $
b101000010010110010100001010 '
b101111 "
b110000 +
1#
#970
0#
#980
b110000 &
b11100101011100110000101011001010 $
b11100101011100110000101011001010 '
b110000 "
bx !
bx (
b110001 +
1#
#990
0#
#1000
b110001 &
bx !
bx (
b10011110001100010100110000111100 $
b10011110001100010100110000111100 '
b110001 "
b110010 +
1#
#1010
0#
#1020
b110010 &
b1111001011010001011110111110010 $
b1111001011010001011110111110010 '
b110010 "
bx !
bx (
b110011 +
1#
#1030
0#
#1040
b110011 &
bx !
bx (
b1000101001011100110000110001010 $
b1000101001011100110000110001010 '
b110011 "
b110100 +
1#
#1050
0#
#1060
b110100 &
b100000110001001011001101000001 $
b100000110001001011001101000001 '
b110100 "
bx !
bx (
b110101 +
1#
#1070
0#
#1080
b110101 &
bx !
bx (
b11101100010010110011010011011000 $
b11101100010010110011010011011000 '
b110101 "
b110110 +
1#
#1090
0#
#1100
b110110 &
b111100001000001111001101111000 $
b111100001000001111001101111000 '
b110110 "
bx !
bx (
b110111 +
1#
#1110
0#
#1120
b110111 &
bx !
bx (
b11000100100010100001001010001001 $
b11000100100010100001001010001001 '
b110111 "
b111000 +
1#
#1130
0#
#1140
b111000 &
b1110101110001010000110111101011 $
b1110101110001010000110111101011 '
b111000 "
bx !
bx (
b111001 +
1#
#1150
0#
#1160
b111001 &
bx !
bx (
b1011011000000100110010110110110 $
b1011011000000100110010110110110 '
b111001 "
b111010 +
1#
#1170
0#
#1180
b111010 &
b1100011010010111111100111000110 $
b1100011010010111111100111000110 '
b111010 "
bx !
bx (
b111011 +
1#
#1190
0#
#1200
b111011 &
bx !
bx (
b1010111000101010001001110101110 $
b1010111000101010001001110101110 '
b111011 "
b111100 +
1#
#1210
0#
#1220
b111100 &
b11011110011101010000001010111100 $
b11011110011101010000001010111100 '
b111100 "
bx !
bx (
b111101 +
1#
#1230
0#
#1240
b111101 &
bx !
bx (
b10101000011111101110100101010 $
b10101000011111101110100101010 '
b111101 "
b111110 +
1#
#1250
0#
#1260
b111110 &
b10000101110101111001101000001011 $
b10000101110101111001101000001011 '
b111110 "
bx !
bx (
b111111 +
1#
#1270
0#
#1280
b111111 &
bx !
bx (
b10111000100101111011111001110001 $
b10111000100101111011111001110001 '
b111111 "
b1000000 +
1#
#1290
0#
#1300
b1000000 &
b1000010111100100100000110000101 $
b1000010111100100100000110000101 '
b1000000 "
bx !
bx (
b1000001 +
1#
#1310
0#
#1320
b1000001 &
bx !
bx (
b100111111100100101010101001111 $
b100111111100100101010101001111 '
b1000001 "
b1000010 +
1#
#1330
0#
#1340
b1000010 &
b10011101110011000110000000111011 $
b10011101110011000110000000111011 '
b1000010 "
bx !
bx (
b1000011 +
1#
#1350
0#
#1360
b1000011 &
bx !
bx (
b11101000001100011001100111010 $
b11101000001100011001100111010 '
b1000011 "
b1000100 +
1#
#1370
0#
#1380
b1000100 &
b10111111001000110011001001111110 $
b10111111001000110011001001111110 '
b1000100 "
bx !
bx (
b1000101 +
1#
#1390
0#
#1400
b1000101 &
bx !
bx (
b1010101010100100101100010101 $
b1010101010100100101100010101 '
b1000101 "
b1000110 +
1#
#1410
0#
#1420
b1000110 &
b1111000110110011001101111110001 $
b1111000110110011001101111110001 '
b1000110 "
bx !
bx (
b1000111 +
1#
#1430
0#
#1440
b1000111 &
bx !
bx (
b1101100100111000100101111011001 $
b1101100100111000100101111011001 '
b1000111 "
b1001000 +
1#
#1450
0#
#1460
b1001000 &
b110001001000110000011101100010 $
b110001001000110000011101100010 '
b1001000 "
bx !
bx (
b1001001 +
1#
#1470
0#
#1480
b1001001 &
bx !
bx (
b100110001101011111101101001100 $
b100110001101011111101101001100 '
b1001001 "
b1001010 +
1#
#1490
0#
#1500
b1001010 &
b1001111101000010101010110011111 $
b1001111101000010101010110011111 '
b1001010 "
bx !
bx (
b1001011 +
1#
#1510
0#
#1520
b1001011 &
bx !
bx (
b1000111101110011010000110001111 $
b1000111101110011010000110001111 '
b1001011 "
b1001100 +
1#
#1530
0#
#1540
b1001100 &
b1111100011011011010100111111000 $
b1111100011011011010100111111000 '
b1001100 "
bx !
bx (
b1001101 +
1#
#1550
0#
#1560
b1001101 &
bx !
bx (
b11011011110011010110000010110111 $
b11011011110011010110000010110111 '
b1001101 "
b1001110 +
1#
#1570
0#
#1580
b1001110 &
b11001111110001000101011010011111 $
b11001111110001000101011010011111 '
b1001110 "
bx !
bx (
b1001111 +
1#
#1590
0#
#1600
b1001111 &
bx !
bx (
b10101110011111011001010001011100 $
b10101110011111011001010001011100 '
b1001111 "
b1010000 +
1#
#1610
0#
#1620
b1010000 &
b10101101110010111100000001011011 $
b10101101110010111100000001011011 '
b1010000 "
bx !
bx (
b1010001 +
1#
#1630
0#
#1640
b1010001 &
bx !
bx (
b1000100110111100011011110001001 $
b1000100110111100011011110001001 '
b1010001 "
b1010010 +
1#
#1650
0#
#1660
b1010010 &
b10100100101011100011001001001001 $
b10100100101011100011001001001001 '
b1010010 "
bx !
bx (
b1010011 +
1#
#1670
0#
#1680
b1010011 &
bx !
bx (
b11101000001000110011111011010000 $
b11101000001000110011111011010000 '
b1010011 "
b1010100 +
1#
#1690
0#
#1700
b1010100 &
b11101011111111101100000011010111 $
b11101011111111101100000011010111 '
b1010100 "
bx !
bx (
b1010101 +
1#
#1710
0#
#1720
b1010101 &
bx !
bx (
b10101000110001111111110001010001 $
b10101000110001111111110001010001 '
b1010101 "
b1010110 +
1#
#1730
0#
#1740
b1010110 &
b1001011001000010010111110010110 $
b1001011001000010010111110010110 '
b1010110 "
bx !
bx (
b1010111 +
1#
#1750
0#
#1760
b1010111 &
bx !
bx (
b110000111010111111100001100 $
b110000111010111111100001100 '
b1010111 "
b1011000 +
1#
#1770
0#
#1780
b1011000 &
b11100001001011001100111011000010 $
b11100001001011001100111011000010 '
b1011000 "
bx !
bx (
b1011001 +
1#
#1790
0#
#1800
b1011001 &
bx !
bx (
b1100100010101111110110111001000 $
b1100100010101111110110111001000 '
b1011001 "
b1011010 +
1#
#1810
0#
#1820
b1011010 &
b10111011100000100101101001110111 $
b10111011100000100101101001110111 '
b1011010 "
bx !
bx (
b1011011 +
1#
#1830
0#
#1840
b1011011 &
bx !
bx (
b11110111100101110110100111101 $
b11110111100101110110100111101 '
b1011011 "
b1011100 +
1#
#1850
0#
#1860
b1011100 &
b1001000011001101101100010010 $
b1001000011001101101100010010 '
b1011100 "
bx !
bx (
b1011101 +
1#
#1870
0#
#1880
b1011101 &
bx !
bx (
b10111111000001010000000001111110 $
b10111111000001010000000001111110 '
b1011101 "
b1011110 +
1#
#1890
0#
#1900
b1011110 &
b110110111001011000000101101101 $
b110110111001011000000101101101 '
b1011110 "
bx !
bx (
b1011111 +
1#
#1910
0#
#1920
b1011111 &
bx !
bx (
b11100110110011110011100111001 $
b11100110110011110011100111001 '
b1011111 "
b1100000 +
1#
#1930
0#
#1940
b1100000 &
b1111110100101000111100011111 $
b1111110100101000111100011111 '
b1100000 "
bx !
bx (
b1100001 +
1#
#1950
0#
#1960
b1100001 &
bx !
bx (
b11101001111010111111011011010011 $
b11101001111010111111011011010011 '
b1100001 "
b1100010 +
1#
#1970
0#
#1980
b1100010 &
b1000010110110010010111110000101 $
b1000010110110010010111110000101 '
b1100010 "
bx !
bx (
b1100011 +
1#
#1990
0#
#2000
b1100011 &
bx !
bx (
b10111100000101001000100001111000 $
b10111100000101001000100001111000 '
b1100011 "
b1100100 +
1#
#2010
0#
#2020
b1100100 &
b101101110110100101100101011011 $
b101101110110100101100101011011 '
b1100100 "
bx !
bx (
b1100101 +
1#
#2030
0#
#2040
b1100101 &
bx !
bx (
b100100100010110100101101001001 $
b100100100010110100101101001001 '
b1100101 "
b1100110 +
1#
#2050
0#
#2060
b1100110 &
b10011111111100101010111000111111 $
b10011111111100101010111000111111 '
b1100110 "
bx !
bx (
b1100111 +
1#
#2070
0#
#2080
b1100111 &
bx !
bx (
b10101000011001010111100101010 $
b10101000011001010111100101010 '
b1100111 "
b1101000 +
1#
#2090
0#
#2100
b1101000 &
b101100000101010110001101011000 $
b101100000101010110001101011000 '
b1101000 "
bx !
bx (
b1101001 +
1#
#2110
0#
#2120
b1101001 &
bx !
bx (
b11000011001111110011100010000110 $
b11000011001111110011100010000110 '
b1101001 "
b1101010 +
1#
#2130
0#
#2140
b1101010 &
b11000111000110100000110010001110 $
b11000111000110100000110010001110 '
b1101010 "
bx !
bx (
b1101011 +
1#
#2150
0#
#2160
b1101011 &
bx !
bx (
b11001110001011111111001010011100 $
b11001110001011111111001010011100 '
b1101011 "
b1101100 +
1#
#2170
0#
#2180
b1101100 &
b1111101001101011001100111111010 $
b1111101001101011001100111111010 '
b1101100 "
bx !
bx (
b1101101 +
1#
#2190
0#
#2200
b1101101 &
bx !
bx (
b10010011011111011011110000100110 $
b10010011011111011011110000100110 '
b1101101 "
b1101110 +
1#
#2210
0#
#2220
b1101110 &
b111001100101100001011101110011 $
b111001100101100001011101110011 '
b1101110 "
bx !
bx (
b1101111 +
1#
#2230
0#
#2240
b1101111 &
bx !
bx (
b11010001100010111011010010100011 $
b11010001100010111011010010100011 '
b1101111 "
b1110000 +
1#
#2250
0#
#2260
b1110000 &
b10010111100110011010100000101111 $
b10010111100110011010100000101111 '
b1110000 "
bx !
bx (
b1110001 +
1#
#2270
0#
#2280
b1110001 &
bx !
bx (
b11011001110100101001001010110011 $
b11011001110100101001001010110011 '
b1110001 "
b1110010 +
1#
#2290
0#
#2300
b1110010 &
b10101111110110000101011001011111 $
b10101111110110000101011001011111 '
b1110010 "
bx !
bx (
b1110011 +
1#
#2310
0#
#2320
b1110011 &
bx !
bx (
b100010001010010000110101000100 $
b100010001010010000110101000100 '
b1110011 "
b1110100 +
1#
#2330
0#
#2340
b1110100 &
b1111011111110001111110111110111 $
b1111011111110001111110111110111 '
b1110100 "
bx !
bx (
b1110101 +
1#
#2350
0#
#2360
b1110101 &
bx !
bx (
b11100101100110110011011011001011 $
b11100101100110110011011011001011 '
b1110101 "
b1110110 +
1#
#2370
0#
#2380
b1110110 &
b11110011000010010001101011100110 $
b11110011000010010001101011100110 '
b1110110 "
bx !
bx (
b1110111 +
1#
#2390
0#
#2400
b1110111 &
bx !
bx (
b101101001010001101101101011010 $
b101101001010001101101101011010 '
b1110111 "
b1111000 +
1#
#2410
0#
#2420
b1111000 &
b10100110011111100000100101001 $
b10100110011111100000100101001 '
b1111000 "
bx !
bx (
b1111001 +
1#
#2430
0#
#2440
b1111001 &
bx !
bx (
b11110110100000101110001011101101 $
b11110110100000101110001011101101 '
b1111001 "
b1111010 +
1#
#2450
0#
#2460
b1111010 &
b11101101010100110110110011011010 $
b11101101010100110110110011011010 '
b1111010 "
bx !
bx (
b1111011 +
1#
#2470
0#
#2480
b1111011 &
bx !
bx (
b10110010100111111011011001100101 $
b10110010100111111011011001100101 '
b1111011 "
b1111100 +
1#
#2490
0#
#2500
b1111100 &
b11011010100010101110001010110101 $
b11011010100010101110001010110101 '
b1111100 "
bx !
bx (
b1111101 +
1#
#2510
0#
#2520
b1111101 &
bx !
bx (
b11101111101111101001010011011111 $
b11101111101111101001010011011111 '
b1111101 "
b1111110 +
1#
#2530
0#
#2540
b1111110 &
b111100111100010001100101111001 $
b111100111100010001100101111001 '
b1111110 "
bx !
bx (
b1111111 +
1#
#2550
0#
#2560
b1111111 &
bx !
bx (
b100010001100011111111101000100 $
b100010001100011111111101000100 '
b1111111 "
b10000000 +
1#
#2570
0#
#2580
b10000000 &
b11101000011101000000110011010000 $
b11101000011101000000110011010000 '
b10000000 "
bx !
bx (
b10000001 +
1#
#2590
0#
#2600
b10000001 &
bx !
bx (
b10101000010010000101100101010 $
b10101000010010000101100101010 '
b10000001 "
b10000010 +
1#
#2610
0#
#2620
b10000010 &
b1010101111101101010110110101011 $
b1010101111101101010110110101011 '
b10000010 "
bx !
bx (
b10000011 +
1#
#2630
0#
#2640
b10000011 &
bx !
bx (
b111011011111100111100001110 $
b111011011111100111100001110 '
b10000011 "
b10000100 +
1#
#2650
0#
#2660
b10000100 &
b1101110010111011010110111011100 $
b1101110010111011010110111011100 '
b10000100 "
bx !
bx (
b10000101 +
1#
#2670
0#
#2680
b10000101 &
bx !
bx (
b11001101010111101011110010011010 $
b11001101010111101011110010011010 '
b10000101 "
b10000110 +
1#
#2690
0#
#2700
b10000110 &
b11111110110111110111001011111101 $
b11111110110111110111001011111101 '
b10000110 "
bx !
bx (
b10000111 +
1#
#2710
0#
#2720
b10000111 &
bx !
bx (
b11100001111100010000001011000011 $
b11100001111100010000001011000011 '
b10000111 "
b10001000 +
1#
#2730
0#
#2740
b10001000 &
b101011000011101110110101010110 $
b101011000011101110110101010110 '
b10001000 "
bx !
bx (
b10001001 +
1#
#2750
0#
#2760
b10001001 &
bx !
bx (
b100111011110011110100101001110 $
b100111011110011110100101001110 '
b10001001 "
b10001010 +
1#
#2770
0#
#2780
b10001010 &
b10110011110110010111011001100111 $
b10110011110110010111011001100111 '
b10001010 "
bx !
bx (
b10001011 +
1#
#2790
0#
#2800
b10001011 &
bx !
bx (
b10000101001100010011010000001010 $
b10000101001100010011010000001010 '
b10001011 "
b10001100 +
1#
#2810
0#
#2820
b10001100 &
b1011011011011111011100110110110 $
b1011011011011111011100110110110 '
b10001100 "
bx !
bx (
b10001101 +
1#
#2830
0#
#2840
b10001101 &
bx !
bx (
b10011100000011101000101000111000 $
b10011100000011101000101000111000 '
b10001101 "
b10001110 +
1#
#2850
0#
#2860
b10001110 &
b111100110100011000011101111001 $
b111100110100011000011101111001 '
b10001110 "
bx !
bx (
b10001111 +
1#
#2870
0#
#2880
b10001111 &
bx !
bx (
b11011100001010111100010010111000 $
b11011100001010111100010010111000 '
b10001111 "
b10010000 +
1#
#2890
0#
#2900
b10010000 &
b1001010011101001011111110010100 $
b1001010011101001011111110010100 '
b10010000 "
bx !
bx (
b10010001 +
1#
#2910
0#
#2920
b10010001 &
bx !
bx (
b1001001110001100101110110010011 $
b1001001110001100101110110010011 '
b10010001 "
b10010010 +
1#
#2930
0#
#2940
b10010010 &
b10000010001111110010110000000100 $
b10000010001111110010110000000100 '
b10010010 "
bx !
bx (
b10010011 +
1#
#2950
0#
#2960
b10010011 &
bx !
bx (
b10101100101101111100101001011001 $
b10101100101101111100101001011001 '
b10010011 "
b10010100 +
1#
#2970
0#
#2980
b10010100 &
b1101101110010110110100111011011 $
b1101101110010110110100111011011 '
b10010100 "
bx !
bx (
b10010101 +
1#
#2990
0#
#3000
b10010101 &
bx !
bx (
b10100110111111001101111001001101 $
b10100110111111001101111001001101 '
b10010101 "
b10010110 +
1#
#3010
0#
#3020
b10010110 &
b1101100101100001011011111011001 $
b1101100101100001011011111011001 '
b10010110 "
bx !
bx (
b10010111 +
1#
#3030
0#
#3040
b10010111 &
bx !
bx (
b10110110101001000010011001101101 $
b10110110101001000010011001101101 '
b10010111 "
b10011000 +
1#
#3050
0#
#3060
b10011000 &
b10111011010001011110001001110110 $
b10111011010001011110001001110110 '
b10011000 "
bx !
bx (
b10011001 +
1#
#3070
0#
#3080
b10011001 &
bx !
bx (
b1100101001110110100100111001010 $
b1100101001110110100100111001010 '
b10011001 "
b10011010 +
1#
#3090
0#
#3100
b10011010 &
b1011011000101110010110110110110 $
b1011011000101110010110110110110 '
b10011010 "
bx !
bx (
b10011011 +
1#
#3110
0#
#3120
b10011011 &
bx !
bx (
b1001010100100110111000110010101 $
b1001010100100110111000110010101 '
b10011011 "
b10011100 +
1#
#3130
0#
#3140
b10011100 &
b10100011000001110001101001000110 $
b10100011000001110001101001000110 '
b10011100 "
bx !
bx (
b10011101 +
1#
#3150
0#
#3160
b10011101 &
bx !
bx (
b10011101001001101100000100 $
b10011101001001101100000100 '
b10011101 "
b10011110 +
1#
#3170
0#
#3180
b10011110 &
b1111011110100100110000111110111 $
b1111011110100100110000111110111 '
b10011110 "
bx !
bx (
b10011111 +
1#
#3190
0#
#3200
b10011111 &
bx !
bx (
b110100100110000000011101101001 $
b110100100110000000011101101001 '
b10011111 "
b10100000 +
1#
#3210
0#
#3220
b10100000 &
b11011010011011101011101010110100 $
b11011010011011101011101010110100 '
b10100000 "
bx !
bx (
b10100001 +
1#
#3230
0#
#3240
b10100001 &
bx !
bx (
b1000100000000011000110110001000 $
b1000100000000011000110110001000 '
b10100001 "
b10100010 +
1#
#3250
0#
#3260
b10100010 &
b10100011111001101100100101000 $
b10100011111001101100100101000 '
b10100010 "
bx !
bx (
b10100011 +
1#
#3270
0#
#3280
b10100011 &
bx !
bx (
b10010110100100000000010000101101 $
b10010110100100000000010000101101 '
b10100011 "
b10100100 +
1#
#3290
0#
#3300
b10100100 &
b11100011110001010011000011000111 $
b11100011110001010011000011000111 '
b10100100 "
bx !
bx (
b10100101 +
1#
#3310
0#
#3320
b10100101 &
bx !
bx (
b10010111010111001001110000101110 $
b10010111010111001001110000101110 '
b10100101 "
b10100110 +
1#
#3330
0#
#3340
b10100110 &
b10000100011101111110010000001000 $
b10000100011101111110010000001000 '
b10100110 "
bx !
bx (
b10100111 +
1#
#3350
0#
#3360
b10100111 &
bx !
bx (
b1110010000010100010100011100 $
b1110010000010100010100011100 '
b10100111 "
b10101000 +
1#
#3370
0#
#3380
b10101000 &
b11111110101001111010011011111101 $
b11111110101001111010011011111101 '
b10101000 "
bx !
bx (
b10101001 +
1#
#3390
0#
#3400
b10101001 &
bx !
bx (
b10100100111100000011100101001 $
b10100100111100000011100101001 '
b10101001 "
b10101010 +
1#
#3410
0#
#3420
b10101010 &
b10001110001101111001000000011100 $
b10001110001101111001000000011100 '
b10101010 "
bx !
bx (
b10101011 +
1#
#3430
0#
#3440
b10101011 &
bx !
bx (
b1000011001101010110011110000110 $
b1000011001101010110011110000110 '
b10101011 "
b10101100 +
1#
#3450
0#
#3460
b10101100 &
b11101101001101000000100011011010 $
b11101101001101000000100011011010 '
b10101100 "
bx !
bx (
b10101101 +
1#
#3470
0#
#3480
b10101101 &
bx !
bx (
b10011110101101111100011000111101 $
b10011110101101111100011000111101 '
b10101101 "
b10101110 +
1#
#3490
0#
#3500
b10101110 &
b110011010011101010011101100110 $
b110011010011101010011101100110 '
b10101110 "
bx !
bx (
b10101111 +
1#
#3510
0#
#3520
b10101111 &
bx !
bx (
b10111000010101011100010001110000 $
b10111000010101011100010001110000 '
b10101111 "
b10110000 +
1#
#3530
0#
#3540
b10110000 &
b10111001111101010000010001110011 $
b10111001111101010000010001110011 '
b10110000 "
bx !
bx (
b10110001 +
1#
#3550
0#
#3560
b10110001 &
bx !
bx (
b1011101011100011001100110111010 $
b1011101011100011001100110111010 '
b10110001 "
b10110010 +
1#
#3570
0#
#3580
b10110010 &
b101111001110101011001101011110 $
b101111001110101011001101011110 '
b10110010 "
bx !
bx (
b10110011 +
1#
#3590
0#
#3600
b10110011 &
bx !
bx (
b1111101010001110111100111111010 $
b1111101010001110111100111111010 '
b10110011 "
b10110100 +
1#
#3610
0#
#3620
b10110100 &
b1101010100011100000010111010101 $
b1101010100011100000010111010101 '
b10110100 "
bx !
bx (
b10110101 +
1#
#3630
0#
#3640
b10110101 &
bx !
bx (
b10001101001001001111011000011010 $
b10001101001001001111011000011010 '
b10110101 "
b10110110 +
1#
#3650
0#
#3660
b10110110 &
b11011100111100000000000010111001 $
b11011100111100000000000010111001 '
b10110110 "
bx !
bx (
b10110111 +
1#
#3670
0#
#3680
b10110111 &
bx !
bx (
b11011100001110110000100110111 $
b11011100001110110000100110111 '
b10110111 "
b10111000 +
1#
#3690
0#
#3700
b10111000 &
b1001011001001110011011110010110 $
b1001011001001110011011110010110 '
b10111000 "
bx !
bx (
b10111001 +
1#
#3710
0#
#3720
b10111001 &
bx !
bx (
b1100000001110010010000111000000 $
b1100000001110010010000111000000 '
b10111001 "
b10111010 +
1#
#3730
0#
#3740
b10111010 &
b10011001001011001111100100110 $
b10011001001011001111100100110 '
b10111010 "
bx !
bx (
b10111011 +
1#
#3750
0#
#3760
b10111011 &
bx !
bx (
b11011011010001100001101010110110 $
b11011011010001100001101010110110 '
b10111011 "
b10111100 +
1#
#3770
0#
#3780
b10111100 &
b111110100110011000001101111101 $
b111110100110011000001101111101 '
b10111100 "
bx !
bx (
b10111101 +
1#
#3790
0#
#3800
b10111101 &
bx !
bx (
b1101110010111110000111111011100 $
b1101110010111110000111111011100 '
b10111101 "
b10111110 +
1#
#3810
0#
#3820
b10111110 &
b1000011011000010101011110000110 $
b1000011011000010101011110000110 '
b10111110 "
bx !
bx (
b10111111 +
1#
#3830
0#
#3840
b10111111 &
bx !
bx (
b111100000000111111111101111000 $
b111100000000111111111101111000 '
b10111111 "
b11000000 +
1#
#3850
0#
#3860
b11000000 &
b111111010110101001101101111110 $
b111111010110101001101101111110 '
b11000000 "
bx !
bx (
b11000001 +
1#
#3870
0#
#3880
b11000001 &
bx !
bx (
b11101101100011011000000011011011 $
b11101101100011011000000011011011 '
b11000001 "
b11000010 +
1#
#3890
0#
#3900
b11000010 &
b11100111110000111011011011001111 $
b11100111110000111011011011001111 '
b11000010 "
bx !
bx (
b11000011 +
1#
#3910
0#
#3920
b11000011 &
bx !
bx (
b111100111011010010101101111001 $
b111100111011010010101101111001 '
b11000011 "
b11000100 +
1#
#3930
0#
#3940
b11000100 &
b11111101001010001110010011111010 $
b11111101001010001110010011111010 '
b11000100 "
bx !
bx (
b11000101 +
1#
#3950
0#
#3960
b11000101 &
bx !
bx (
b10110000101111001110111001100001 $
b10110000101111001110111001100001 '
b11000101 "
b11000110 +
1#
#3970
0#
